{
    "id": "brown",
    "name": "悦灵雅棕",
    "styles": {
        "container": "",
        "title": {
            "h1": {
                "base": "margin: 32px 0 0; font-size: 2em; letter-spacing: -0.02em; line-height: 1.5;",
                "content": "font-weight: bold; color: #4a4a4a;",
                "after": ""
            },
            "h2": {
                "base": "margin: 28px 0 24px 0; font-size: 1.5em; letter-spacing: -0.01em; line-height: 1.5;",
                "content": "font-weight: bold; color: #4a4a4a;",
                "after": ""
            },
            "h3": {
                "base": "margin: 24px 0 20px 0; font-size: 1.25em; letter-spacing: -0.01em; border-left: 4px solid #4a4a4a; padding-left: 12px; line-height: 1.5;",
                "content": "font-weight: bold; color: #4a4a4a;",
                "after": ""
            },
            "base": {
                "base": "margin: 20px 0 0; font-size: 1em; line-height: 1.5;",
                "content": "font-weight: bold; color: #4a4a4a;",
                "after": ""
            }
        },
        "paragraph": "line-height: 1.8; margin-top: 1em; font-size: 1em; color: #4a4a4a;",
        "list": {
            "container": "padding-left: 32px; color: #4a4a4a;",
            "item": "font-size: 1em; color: #4a4a4a; line-height: 1.8;",
            "taskList": "list-style: none; font-size: 1em; color: #4a4a4a; line-height: 1.8;"
        },
        "code": {
            "header": {
            "container": "margin-bottom: 1em; display: flex; gap: 6px;",
            "dot": "width: 12px; height: 12px; border-radius: 50%;",
            "colors": [
              "#ff5f56",
              "#ffbd2e",
              "#27c93f"
            ]
          },
          "block": "color: #333; background: #fef7ed; border-radius: 8px; border: 1px solid #f5e2c7; box-shadow: 0 2px 4px rgba(0,0,0,0.05); margin: 1.2em 0; padding: 1em 1em 1em;  font-size: 14px; line-height: 1.6; white-space: pre-wrap;",
            "inline": "background: #fef7ed; padding: 2px 6px; border-radius: 4px; color: #333; font-size: 14px; border: 1px solid #f5e2c7;"
        },
        "quote": "border-left: 4px solid #c57512; border-radius: 6px; padding: 10px 10px; background: #fef7ed; margin: 0.8em 0; color: #8b6d4d; font-style: italic; word-wrap: break-word;",
        "image": "max-width: 100%; height: auto; margin: 1em auto; display: block;",
        "link": "color: #c57512; text-decoration: none; border-bottom: 1px solid #c57512;",
        "emphasis": {
            "strong": "font-weight: bold; color: #c57512;",
            "em": "font-style: italic; color: #c57512;",
            "del": "text-decoration: line-through; color: #c57512;"
        },
        "table": {
            "container": "width: 100%; margin: 1em 0; border-collapse: collapse; border: 1px solid #f5e2c7;",
            "header": "background: #fef7ed; font-weight: bold; color: #c57512; border-bottom: 2px solid #f5e2c7; font-size: 1em;",
            "cell": "border: 1px solid #f5e2c7; padding: 8px; color: #4a4a4a; font-size: 1em;"
        },
        "hr": "border: none; border-top: 1px solid #f5e2c7; margin: 20px 0;",
        "footnote": {
            "ref": "color: #c57512; text-decoration: none; font-size: 0.9em;",
            "backref": "color: #c57512; text-decoration: none; font-size: 0.9em;"
        }
    }
}